[
  {
    "outline": [
      {
        "type": "M",
        "x": 480.623,
        "y": 145.365
      },
      {
        "type": "C",
        "begin": {
          "x": 851.555,
          "y": 545.979
        },
        "mid": {
          "x": 516.009,
          "y": 167.796
        },
        "end": {
          "x": 795.864,
          "y": 481.186
        }
      },
      {
        "type": "C",
        "begin": {
          "x": 1289.94,
          "y": 1071.45
        },
        "mid": {
          "x": 877.661,
          "y": 576.352
        },
        "end": {
          "x": 1274.37,
          "y": 1055.04
        }
      },
      {
        "type": "C",
        "begin": {
          "x": 1897.94,
          "y": 1812.24
        },
        "mid": {
          "x": 1305.61,
          "y": 1087.95
        },
        "end": {
          "x": 1881.01,
          "y": 1790.03
        }
      },
      {
        "type": "C",
        "begin": {
          "x": 1875.36,
          "y": 1940.49
        },
        "mid": {
          "x": 1935.55,
          "y": 1861.57
        },
        "end": {
          "x": 1917.14,
          "y": 1928.37
        }
      },
      {
        "type": "C",
        "begin": {
          "x": 1376.82,
          "y": 1514.94
        },
        "mid": {
          "x": 1829.21,
          "y": 1953.89
        },
        "end": {
          "x": 1806.65,
          "y": 1937.17
        }
      },
      {
        "type": "C",
        "begin": {
          "x": 518.076,
          "y": 777.694
        },
        "mid": {
          "x": 1247.89,
          "y": 1388.3
        },
        "end": {
          "x": 715.077,
          "y": 928.201
        }
      },
      {
        "type": "C",
        "begin": {
          "x": 128.255,
          "y": 518.235
        },
        "mid": {
          "x": 365.381,
          "y": 661.036
        },
        "end": {
          "x": 218.449,
          "y": 575.582
        }
      },
      {
        "type": "C",
        "begin": {
          "x": 105.381,
          "y": 423.062
        },
        "mid": {
          "x": 92.193,
          "y": 495.306
        },
        "end": {
          "x": 82.308,
          "y": 452.322
        }
      },
      {
        "type": "C",
        "begin": {
          "x": 384.28,
          "y": 159.982
        },
        "mid": {
          "x": 157.476,
          "y": 356.997
        },
        "end": {
          "x": 314.947,
          "y": 210.54
        }
      },
      {
        "type": "C",
        "begin": {
          "x": 480.623,
          "y": 145.365
        },
        "mid": {
          "x": 427.667,
          "y": 128.343
        },
        "end": {
          "x": 457.323,
          "y": 130.596
        }
      }
    ],
    "track": []
  }
]